{
  "pkg_discounts": {
    "Sanding Photography": {
      "v": 0,
      "t": "fixed"
    },
    "Nikah + Sanding Video": {
      "v": 0,
      "t": "fixed"
    },
    "Full Package Video": {
      "v": 0,
      "t": "fixed"
    },
    "Tunang Photography": {
      "v": 0,
      "t": "fixed"
    },
    "Nikah Photography": {
      "v": 0,
      "t": "fixed"
    },
    "Nikah Video": {
      "v": 0,
      "t": "fixed"
    },
    "TRIO E (3 Events)": {
      "v": 0,
      "t": "fixed"
    },
    "Nikah & Sanding Photography": {
      "v": 0,
      "t": "fixed"
    },
    "Tunang + Nikah + Sanding": {
      "v": 0,
      "t": "fixed"
    },
    "Pre Wed Photography": {
      "v": 0,
      "t": "fixed"
    }
  },
  "promo_codes": {}
}